cookieutils/__init__.py
cookieutils/clear.py
cookieutils/codes.py
cookieutils/colors.py
cookieutils/key.py
cookieutils/keys.py
cookieutils/utils.py
cookieutils-0.0.4.dist-info/LICENCE
cookieutils-0.0.4.dist-info/METADATA
cookieutils-0.0.4.dist-info/WHEEL
cookieutils-0.0.4.dist-info/top_level.txt
cookieutils-0.0.4.dist-info/RECORD
