Metadata-Version: 2.1
Name: cookieutils
Version: 0.0.4
Summary: A ton of usefull utils for python console applications
Home-page: https://github.com/Epic-Oreo/cookieutils
Author: Epic Oreo
Author-email: none@example.com
Project-URL: Bug Tracker, https://github.com/Epic-Oreo/cookieutils/issues
Classifier: Programming Language :: Python :: 3
Classifier: License :: OSI Approved :: MIT License
Classifier: Operating System :: OS Independent
Requires-Python: >=3.6
License-File: LICENCE
